xontrib/zoxide/__init__.py
xontrib/zoxide/zoxide.py
xontrib/zoxide/zoxide_init_cache.py
xontrib_zoxide-1.1.0.dist-info/LICENSE
xontrib_zoxide-1.1.0.dist-info/METADATA
xontrib_zoxide-1.1.0.dist-info/WHEEL
xontrib_zoxide-1.1.0.dist-info/RECORD
