Metadata-Version: 2.1
Name: xontrib-zoxide
Version: 1.1.0
Summary: Zoxide integration for xonsh
Home-page: https://github.com/dyuri/xontrib-zoxide
License: MIT
Keywords: xontrib,xonsh
Author: Gyuri Horak
Author-email: dyuri@horak.hu
Requires-Python: >=3.7
Classifier: Intended Audience :: Developers
Classifier: License :: OSI Approved :: MIT License
Classifier: Natural Language :: English
Classifier: Operating System :: OS Independent
Classifier: Programming Language :: Python :: 3
Classifier: Programming Language :: Python :: 3.7
Classifier: Programming Language :: Python :: 3.8
Classifier: Programming Language :: Python :: 3.9
Classifier: Programming Language :: Python :: 3.10
Classifier: Programming Language :: Python :: 3.11
Classifier: Programming Language :: Python :: 3.12
Classifier: Topic :: System :: Shells
Classifier: Topic :: System :: System Shells
Classifier: Topic :: Terminals
Requires-Dist: xonsh (>=0.12.5)
Project-URL: Code, https://github.com/dyuri/xontrib-zoxide
Project-URL: Documentation, https://github.com/dyuri/xontrib-zoxide/blob/master/README.md
Project-URL: Issue tracker, https://github.com/dyuri/xontrib-zoxide/issues
Project-URL: Repository, https://github.com/dyuri/xontrib-zoxide
